onepassword.py
awsume_1password_gaiden-0.0.2.dist-info/licenses/LICENSE
awsume_1password_gaiden-0.0.2.dist-info/METADATA
awsume_1password_gaiden-0.0.2.dist-info/WHEEL
awsume_1password_gaiden-0.0.2.dist-info/entry_points.txt
awsume_1password_gaiden-0.0.2.dist-info/top_level.txt
awsume_1password_gaiden-0.0.2.dist-info/RECORD
