Metadata-Version: 2.4
Name: awsume-1password-gaiden
Version: 0.0.2
Summary: Fetches AWS access keys and MFA from 1Password
Home-page: https://github.com/samsimpson1/awsume-1password
Author: Sam Simpson
Author-email: pypi@sams.wtf
License-File: LICENSE
Dynamic: author
Dynamic: author-email
Dynamic: description
Dynamic: home-page
Dynamic: license-file
Dynamic: summary
